odoo8_addon_document_rtf_index-8.0.1.0.0-py2.7-nspkg.pth
odoo_addons/document_rtf_index/__openerp__.py
odoo_addons/document_rtf_index/__init__.py
odoo_addons/document_rtf_index/README.rst
odoo_addons/document_rtf_index/models/__init__.py
odoo_addons/document_rtf_index/models/ir_attachment.py
odoo_addons/document_rtf_index/test_files/test_with_cat_image.rtf
odoo_addons/document_rtf_index/tests/test_rtf_index.py
odoo_addons/document_rtf_index/tests/__init__.py
odoo_addons/document_rtf_index/static/description/icon.png
odoo8_addon_document_rtf_index-8.0.1.0.0.dist-info/top_level.txt
odoo8_addon_document_rtf_index-8.0.1.0.0.dist-info/WHEEL
odoo8_addon_document_rtf_index-8.0.1.0.0.dist-info/RECORD
odoo8_addon_document_rtf_index-8.0.1.0.0.dist-info/metadata.json
odoo8_addon_document_rtf_index-8.0.1.0.0.dist-info/DESCRIPTION.rst
odoo8_addon_document_rtf_index-8.0.1.0.0.dist-info/METADATA
odoo8_addon_document_rtf_index-8.0.1.0.0.dist-info/namespace_packages.txt
